{
  "oreMultiplier": 1,
  "ores": [
    {
      "ore_size": 3,
      "discard_on_air_chance": 0.0,
      "modifiers": [
        {
          "count": 2,
          "type": "minecraft:count"
        },
        {
          "type": "minecraft:in_square"
        },
        {
          "height": {
            "min_inclusive": {
              "absolute": 10
            },
            "max_inclusive": {
              "absolute": 30
            },
            "type": "minecraft:trapezoid"
          },
          "type": "minecraft:height_range"
        },
        {
          "type": "minecraft:biome"
        }
      ],
      "targets": [
        {
          "target": {
            "block": "minecraft:end_stone",
            "predicate_type": "minecraft:block_match"
          },
          "state": {
            "Name": "lolenderite:primordial_remnants"
          }
        }
      ]
    },
    {
      "ore_size": 10,
      "discard_on_air_chance": 0.0,
      "modifiers": [
        {
          "count": 8,
          "type": "minecraft:count"
        },
        {
          "type": "minecraft:in_square"
        },
        {
          "height": {
            "min_inclusive": {
              "absolute": 2
            },
            "max_inclusive": {
              "absolute": 80
            },
            "type": "minecraft:uniform"
          },
          "type": "minecraft:height_range"
        },
        {
          "type": "minecraft:biome"
        }
      ],
      "targets": [
        {
          "target": {
            "tag": "minecraft:end_stones",
            "predicate_type": "minecraft:tag_match"
          },
          "state": {
            "Name": "rftoolsbase:dimensionalshard_end"
          }
        }
      ]
    },
    {
      "ore_size": 50,
      "discard_on_air_chance": 0.0,
      "modifiers": [
        {
          "count": 60,
          "type": "minecraft:count"
        },
        {
          "type": "minecraft:in_square"
        },
        {
          "height": {
            "min_inclusive": {
              "above_bottom": 0
            },
            "max_inclusive": {
              "below_top": 0
            },
            "type": "minecraft:uniform"
          },
          "type": "minecraft:height_range"
        },
        {
          "type": "minecraft:biome"
        }
      ],
      "targets": [
        {
          "target": {
            "block": "minecraft:calcite",
            "predicate_type": "minecraft:block_match"
          },
          "state": {
            "Name": "minecraft:snow_block"
          }
        },
        {
          "target": {
            "block": "minecraft:end_stone",
            "predicate_type": "minecraft:block_match"
          },
          "state": {
            "Name": "minecraft:snow_block"
          }
        },
        {
          "target": {
            "block": "minecraft:diorite",
            "predicate_type": "minecraft:block_match"
          },
          "state": {
            "Name": "minecraft:snow_block"
          }
        },
        {
          "target": {
            "block": "minecraft:netherrack",
            "predicate_type": "minecraft:block_match"
          },
          "state": {
            "Name": "minecraft:snow_block"
          }
        }
      ]
    },
    {
      "ore_size": 50,
      "discard_on_air_chance": 0.0,
      "modifiers": [
        {
          "count": 45,
          "type": "minecraft:count"
        },
        {
          "type": "minecraft:in_square"
        },
        {
          "height": {
            "min_inclusive": {
              "above_bottom": 0
            },
            "max_inclusive": {
              "below_top": 0
            },
            "type": "minecraft:uniform"
          },
          "type": "minecraft:height_range"
        },
        {
          "type": "minecraft:biome"
        }
      ],
      "targets": [
        {
          "target": {
            "block": "minecraft:packed_ice",
            "predicate_type": "minecraft:block_match"
          },
          "state": {
            "Name": "minecraft:blue_ice"
          }
        }
      ]
    },
    {
      "ore_size": 64,
      "discard_on_air_chance": 0.0,
      "modifiers": [
        {
          "count": 100,
          "type": "minecraft:count_on_every_layer"
        },
        {
          "type": "minecraft:biome"
        }
      ],
      "targets": [
        {
          "target": {
            "block": "minecraft:sculk_shrieker",
            "predicate_type": "minecraft:block_match"
          },
          "state": {
            "Name": "minecraft:air"
          }
        }
      ]
    }
  ]
}